kurbopy-0.11.1.dist-info/METADATA
kurbopy-0.11.1.dist-info/WHEEL
kurbopy-0.11.1.dist-info/licenses/LICENSE.txt
kurbopy/common/__init__.py
kurbopy/magic.py
kurbopy/__init__.py
kurbopy/kurbopy.pyd
kurbopy-0.11.1.dist-info/RECORD
