Metadata-Version: 2.3
Name: kurbopy
Version: 0.11.1
Classifier: Programming Language :: Rust
Requires-Dist: fonttools >=4.0
License-File: LICENSE.txt
Author: Simon Cozens <simon@simon-cozens.org>
Author-email: Simon Cozens <simon@simon-cozens.org>
Requires-Python: >=3.7
